dataviz_generator/__init__.py
dataviz_generator/generator.py
dataviz_generator-0.1.1.dist-info/LICENSE
dataviz_generator-0.1.1.dist-info/METADATA
dataviz_generator-0.1.1.dist-info/WHEEL
dataviz_generator-0.1.1.dist-info/top_level.txt
dataviz_generator-0.1.1.dist-info/RECORD
